MANIFEST.in
setup.py
docs/HISTORY.txt
src/dolmen/__init__.py
src/dolmen.file.egg-info/PKG-INFO
src/dolmen.file.egg-info/SOURCES.txt
src/dolmen.file.egg-info/dependency_links.txt
src/dolmen.file.egg-info/namespace_packages.txt
src/dolmen.file.egg-info/not-zip-safe
src/dolmen.file.egg-info/requires.txt
src/dolmen.file.egg-info/top_level.txt
src/dolmen/file/README.txt
src/dolmen/file/__init__.py
src/dolmen/file/access.py
src/dolmen/file/chunk.py
src/dolmen/file/configure.zcml
src/dolmen/file/field.py
src/dolmen/file/file.py
src/dolmen/file/ftesting.zcml
src/dolmen/file/property.py
src/dolmen/file/size.py
src/dolmen/file/tests.py
src/dolmen/file/utils.py