Metadata-Version: 1.0
Name: dolmen.file
Version: 0.6
Summary: A Zope3/Grok File Representation package.
Home-page: UNKNOWN
Author: Souheil Chelfouh
Author-email: trollfot@gmail.com
License: GPL
Keywords: Grok Zope3 file download
Platform: UNKNOWN
Classifier: Environment :: Web Environment
Classifier: Framework :: Zope3
Classifier: Intended Audience :: Other Audience
Classifier: License :: OSI Approved :: GNU General Public License (GPL)
Classifier: Operating System :: OS Independent
Classifier: Programming Language :: Python
